cjwpandasmodule/__init__.py
cjwpandasmodule/convert.py
cjwpandasmodule/validate.py
cjwpandasmodule-0.2.0.dist-info/WHEEL
cjwpandasmodule-0.2.0.dist-info/METADATA
cjwpandasmodule-0.2.0.dist-info/RECORD
