Metadata-Version: 2.1
Name: cjwpandasmodule
Version: 0.2.0
Summary: Utilities for Workbench modules that use Pandas
License: MIT
Author: Adam Hooper
Author-email: adam@adamhooper.com
Requires-Python: >=3.8.0,<3.9.0
Classifier: License :: OSI Approved :: MIT License
Classifier: Programming Language :: Python :: 3
Classifier: Programming Language :: Python :: 3.8
Requires-Dist: cjwmodule (>=4.0,<5.0)
Requires-Dist: pandas (>=0.25.0,<0.26.0)
